docprint/__init__.py
docprint/cache/__init__.py
docprint/cache/flush.py
docprint/cache/manager.py
docprint/config/__init__.py
docprint/config/constants.py
docprint/content/__init__.py
docprint/content/layout_utils.py
docprint/content/matcher.py
docprint/content/formatters/__init__.py
docprint/content/formatters/base.py
docprint/content/formatters/chart.py
docprint/content/formatters/content_basic.py
docprint/content/formatters/content_rich.py
docprint/content/formatters/divider.py
docprint/content/formatters/layout.py
docprint/content/formatters/structural.py
docprint/content/formatters/visual.py
docprint/core/__init__.py
docprint/core/docprint_func.py
docprint/files/__init__.py
docprint/files/handler.py
docprint/github/__init__.py
docprint/github/auth.py
docprint/github/syncer.py
docprint/github/timer.py
docprint-1.2.5.dist-info/licenses/LICENSE
docprint-1.2.5.dist-info/METADATA
docprint-1.2.5.dist-info/WHEEL
docprint-1.2.5.dist-info/top_level.txt
docprint-1.2.5.dist-info/RECORD
