Metadata-Version: 2.4
Name: DocPrint
Version: 1.2.5
Summary: Runtime documentation generation tool for live markdown output
Author-email: Jay Baleine <jay@banes-lab.com>
License: Copyright 2025 Jay Baleine (https://github.com/Varietyz https://banes-lab.com)
Project-URL: Homepage, https://github.com/Varietyz/DocPrint
Project-URL: Repository, https://github.com/Varietyz/DocPrint
Project-URL: Issues, https://github.com/Varietyz/DocPrint/issues
Keywords: documentation,markdown,runtime,logging
Classifier: Development Status :: 4 - Beta
Classifier: Intended Audience :: Developers
Classifier: License :: OSI Approved :: MIT License
Classifier: Programming Language :: Python :: 3
Classifier: Programming Language :: Python :: 3.7
Classifier: Programming Language :: Python :: 3.8
Classifier: Programming Language :: Python :: 3.9
Classifier: Programming Language :: Python :: 3.10
Classifier: Programming Language :: Python :: 3.11
Classifier: Programming Language :: Python :: 3.12
Classifier: Topic :: Documentation
Classifier: Topic :: Software Development :: Documentation
Classifier: Topic :: System :: Logging
Requires-Python: >=3.7
License-File: LICENSE
Requires-Dist: regex>=2025.9.1
Requires-Dist: xxhash>=3.5.0
Provides-Extra: performance
Requires-Dist: ujson>=5.11.0; extra == "performance"
Requires-Dist: orjson>=3.11.3; extra == "performance"
Dynamic: license-file
